subliminal/__init__.py
subliminal/__main__.py
subliminal/archives.py
subliminal/cache.py
subliminal/core.py
subliminal/exceptions.py
subliminal/extensions.py
subliminal/matches.py
subliminal/py.typed
subliminal/score.py
subliminal/subtitle.py
subliminal/utils.py
subliminal/video.py
subliminal/cli/__init__.py
subliminal/cli/cli.py
subliminal/cli/generate_config.py
subliminal/cli/helpers.py
subliminal/cli/commands/__init__.py
subliminal/cli/commands/_format.py
subliminal/cli/commands/download_best.py
subliminal/converters/__init__.py
subliminal/converters/addic7ed.py
subliminal/converters/opensubtitles.py
subliminal/converters/opensubtitlescom.py
subliminal/converters/subtitulamos.py
subliminal/converters/tvsubtitles.py
subliminal/providers/__init__.py
subliminal/providers/addic7ed.py
subliminal/providers/bsplayer.py
subliminal/providers/gestdown.py
subliminal/providers/mock.py
subliminal/providers/napiprojekt.py
subliminal/providers/opensubtitles.py
subliminal/providers/opensubtitlescom.py
subliminal/providers/podnapisi.py
subliminal/providers/subtitulamos.py
subliminal/providers/tvsubtitles.py
subliminal/refiners/__init__.py
subliminal/refiners/hash.py
subliminal/refiners/metadata.py
subliminal/refiners/omdb.py
subliminal/refiners/tmdb.py
subliminal/refiners/tvdb.py
subliminal-2.4.0.dist-info/METADATA
subliminal-2.4.0.dist-info/WHEEL
subliminal-2.4.0.dist-info/entry_points.txt
subliminal-2.4.0.dist-info/licenses/LICENSE
subliminal-2.4.0.dist-info/RECORD
