Metadata-Version: 2.4
Name: subliminal
Version: 2.4.0
Summary: Subtitles, faster than your thoughts
Project-URL: homepage, https://github.com/Diaoul/subliminal
Project-URL: repository, https://github.com/Diaoul/subliminal
Project-URL: documentation, https://subliminal.readthedocs.org
Author-email: Antoine Bertin <diaoulael@gmail.com>
Maintainer-email: Antoine Bertin <diaoulael@gmail.com>, getzze <getzze@gmail.com>, Patrycja Rosa <pypi@ptrcnull.me>
License: MIT
License-File: LICENSE
Keywords: episode,movie,series,show,subtitle,subtitles,tv,video
Classifier: Development Status :: 5 - Production/Stable
Classifier: Intended Audience :: Developers
Classifier: License :: OSI Approved :: MIT License
Classifier: Operating System :: OS Independent
Classifier: Programming Language :: Python
Classifier: Programming Language :: Python :: 3
Classifier: Programming Language :: Python :: 3.9
Classifier: Programming Language :: Python :: 3.10
Classifier: Programming Language :: Python :: 3.11
Classifier: Programming Language :: Python :: 3.12
Classifier: Programming Language :: Python :: 3.13
Classifier: Topic :: Multimedia :: Video
Classifier: Topic :: Software Development :: Libraries :: Python Modules
Requires-Python: >=3.9
Requires-Dist: babelfish>=0.6.1
Requires-Dist: beautifulsoup4>=4.4.0
Requires-Dist: chardet>=5.0
Requires-Dist: click-option-group>=0.5.6
Requires-Dist: click>=8.0
Requires-Dist: defusedxml>=0.7.1
Requires-Dist: dogpile-cache>=1.0
Requires-Dist: guessit>=3.0.0
Requires-Dist: knowit>=0.5.5
Requires-Dist: platformdirs>=3
Requires-Dist: pysubs2>=1.7
Requires-Dist: requests>=2.0
Requires-Dist: srt>=3.5
Requires-Dist: stevedore>=3.0
Requires-Dist: tomlkit>=0.13.2
Provides-Extra: dev
Requires-Dist: pre-commit>=2.9.3; extra == 'dev'
Requires-Dist: tox; extra == 'dev'
Provides-Extra: docs
Requires-Dist: sphinx-autodoc-typehints; extra == 'docs'
Requires-Dist: sphinx-changelog; extra == 'docs'
Requires-Dist: sphinx-rtd-theme>=2; extra == 'docs'
Requires-Dist: sphinx<8.2; extra == 'docs'
Requires-Dist: sphinxcontrib-programoutput; extra == 'docs'
Requires-Dist: towncrier; extra == 'docs'
Requires-Dist: vcrpy>=5; extra == 'docs'
Provides-Extra: rar
Requires-Dist: rarfile>=2.7; extra == 'rar'
Provides-Extra: tests
Requires-Dist: colorama; extra == 'tests'
Requires-Dist: coverage[toml]>=7; extra == 'tests'
Requires-Dist: importlib-metadata>=4.6; (python_version < '3.10') and extra == 'tests'
Requires-Dist: pytest-cov; extra == 'tests'
Requires-Dist: pytest-xdist; extra == 'tests'
Requires-Dist: pytest>=6.0; extra == 'tests'
Requires-Dist: rarfile>=2.7; extra == 'tests'
Requires-Dist: sympy; extra == 'tests'
Requires-Dist: vcrpy>=5; extra == 'tests'
Requires-Dist: win32-setctime; (sys_platform == 'win32') and extra == 'tests'
Provides-Extra: types
Requires-Dist: mypy; extra == 'types'
Requires-Dist: types-beautifulsoup4; extra == 'types'
Requires-Dist: types-decorator; extra == 'types'
Requires-Dist: types-requests; extra == 'types'
